README.rst
setup.py
huaweicloud_python_sdk_core.egg-info/PKG-INFO
huaweicloud_python_sdk_core.egg-info/SOURCES.txt
huaweicloud_python_sdk_core.egg-info/dependency_links.txt
huaweicloud_python_sdk_core.egg-info/requires.txt
huaweicloud_python_sdk_core.egg-info/top_level.txt
huaweipythonsdkcore/__init__.py
huaweipythonsdkcore/base_client.py
huaweipythonsdkcore/client.py
huaweipythonsdkcore/credential.py
huaweipythonsdkcore/endpoint_resolver.py
huaweipythonsdkcore/exception.py
huaweipythonsdkcore/request.py
huaweipythonsdkcore/urllib3_handler.py
huaweipythonsdkcore/utils.py
huaweipythonsdkcore/auth/__init__.py
huaweipythonsdkcore/auth/aksk_authenticator.py
huaweipythonsdkcore/auth/authenticator.py
huaweipythonsdkcore/auth/digester.py
huaweipythonsdkcore/auth/factory.py
huaweipythonsdkcore/auth/pwd_authenticator.py
huaweipythonsdkcore/auth/utils.py
tests/__init__.py
tests/functional/__init__.py
tests/functional/test_aksk_credential.py
tests/functional/test_pwd_credential.py
tests/functional/utils.py
tests/unit/__init__.py
tests/unit/test_utils.py