Metadata-Version: 1.2
Name: huaweicloud-python-sdk-core
Version: 0.0.3
Summary: HuaweiCloud Python SDK Core
Home-page: https://github.com/huaweicloud/huaweicloud-python-sdk-core
Author: Huawei Cloud
Maintainer-email: support@huaweicloud.com
License: Apache License 2.0
Platform: any
Classifier: Development Status :: 5 - Production/Stable
Classifier: Intended Audience :: Developers
Classifier: License :: OSI Approved :: Apache Software License
Classifier: Programming Language :: Python
Classifier: Programming Language :: Python :: 2.7
Classifier: Programming Language :: Python :: 3
Classifier: Programming Language :: Python :: 3.1
Classifier: Programming Language :: Python :: 3.2
Classifier: Programming Language :: Python :: 3.3
Classifier: Programming Language :: Python :: 3.4
Classifier: Programming Language :: Python :: 3.5
Classifier: Programming Language :: Python :: 3.6
